[
    {
        "assetName": "Laptop",
        "assetPrice": 1200,
        "assetType": "Returnable",
        "assetImage": "https://i.ibb.co/wQHhbkM/Computer.webp",
        "whyNeeded": "Upgrade for better performance",
        "additionalInfo": "Requires higher processing power and more storage"
    },
    {
        "assetName": "Pens",
        "assetPrice": 2,
        "assetType": "Non-returnable",
        "assetImage": "https://i.ibb.co/k4kxYpB/Pens.webp",
        "whyNeeded": "Restocking office supplies",
        "additionalInfo": "Black ink preferred"
    },
    {
        "assetName": "Desk",
        "assetPrice": 350,
        "assetType": "Returnable",
        "assetImage": "https://i.ibb.co/TMS7JPb/Desk.webp",
        "whyNeeded": "Workspace expansion",
        "additionalInfo": "Needs to accommodate dual monitors"
    },
    {
        "assetName": "Cell Phones",
        "assetPrice": 800,
        "assetType": "Returnable",
        "assetImage": "https://i.ibb.co/KsJ8mfN/phone.jpg",
        "whyNeeded": "Mobile device upgrade",
        "additionalInfo": "Require latest iOS/Android versions"
    },
    {
        "assetName": "Diaries",
        "assetPrice": 5,
        "assetType": "Non-returnable",
        "assetImage": "https://i.ibb.co/4tYjDhC/Diaries.jpg",
        "whyNeeded": "Yearly office supplies renewal",
        "additionalInfo": "Prefer hardcover"
    },
    {
        "assetName": "Chair",
        "assetPrice": 150,
        "assetType": "Returnable",
        "assetImage": "https://i.ibb.co/3cH5GQk/Chair.jpg",
        "whyNeeded": "Ergonomic seating for improved comfort",
        "additionalInfo": "Requires adjustable height and lumbar support"
    }
]